xrvoyage/__init__.py
xrvoyage/_version.py
xrvoyage/common/__init__.py
xrvoyage/common/config.py
xrvoyage/common/exceptions.py
xrvoyage/common/static.py
xrvoyage/entities/data.py
xrvoyage/entities/data_webhook.py
xrvoyage/entities/job.py
xrvoyage/entities/panel.py
xrvoyage/entities/planet.py
xrvoyage/entities/plugin.py
xrvoyage/entities/ship.py
xrvoyage/entities/webhooks_xrweb.py
xrvoyage/handlers/__init__.py
xrvoyage/handlers/auth.py
xrvoyage/handlers/decorators.py
xrvoyage/handlers/http.py
xrvoyage/handlers/wss.py
xrvoyage/models/__init__.py
xrvoyage/models/data.py
xrvoyage/models/events.py
xrvoyage/models/panel.py
xrvoyage/models/planet.py
xrvoyage/models/plugin.py
xrvoyage/models/ship.py
xrvoyage/xr_api_client.py
xrvoyage-1.1.24.dist-info/LICENSE
xrvoyage-1.1.24.dist-info/METADATA
xrvoyage-1.1.24.dist-info/WHEEL
xrvoyage-1.1.24.dist-info/RECORD
