Metadata-Version: 2.1
Name: xrvoyage
Version: 1.1.24
Summary: XR Voyage Python Package
Author: Peter Styk
Author-email: peter@neux.io
Requires-Python: >=3.11.0
Classifier: Programming Language :: Python :: 3
Classifier: Programming Language :: Python :: 3.11
Classifier: Programming Language :: Python :: 3.12
Requires-Dist: lionagi (>=0.2.1,<0.3.0)
Requires-Dist: logzero (>=1.7.0,<2.0.0)
Requires-Dist: pydantic (>=2.7.1,<3.0.0)
Requires-Dist: pyjwt (>=2.8.0,<3.0.0)
Requires-Dist: python-decouple (>=3.8,<4.0)
Requires-Dist: requests (>=2.32.2,<3.0.0)
Requires-Dist: websockets (>=12.0,<13.0)
